usograf/__init__.py
usograf/funcgraficos.py
usograf-1.0.dist-info/METADATA
usograf-1.0.dist-info/WHEEL
usograf-1.0.dist-info/top_level.txt
usograf-1.0.dist-info/RECORD
