Metadata-Version: 2.1
Name: usograf
Version: 1.0
Summary: Funciones para Graficos del curso para FISI UNMSM
Home-page: https://dina.concytec.gob.pe/appDirectorioCTI/VerDatosInvestigador.do?id_investigador=12581
Author: Jorge Guerra Guerra
Author-email: jguerra91@gmail.com
License: UNKNOWN
Platform: UNKNOWN
